<!DOCTYPE document [
  <!-- These are the entity sets for ISO Latin 1 characters for the XHTML -->
  <!ENTITY % HTMLlat1 PUBLIC "-//W3C//ENTITIES Latin 1 for XHTML//EN" "http://www.w3.org/TR/xhtml1/DTD/xhtml-lat1.ent">
  %HTMLlat1;
  <!-- These are the entity sets for special characters for the XHTML -->
  <!ENTITY % HTMLsymbol PUBLIC "-//W3C//ENTITIES Symbols for XHTML//EN" "http://www.w3.org/TR/xhtml1/DTD/xhtml-symbol.ent">
  %HTMLsymbol;
  <!-- These are the entity sets for symbol characters for the XHTML -->
  <!ENTITY % HTMLspecial PUBLIC "-//W3C//ENTITIES Special for XHTML//EN" "http://www.w3.org/TR/xhtml1/DTD/xhtml-special.ent">
  %HTMLspecial;
]>
<document xmlns="http://maven.apache.org/XDOC/2.0" xmlns:xsi="http://www.w3.org/2001/XMLSchema-instance" xsi:schemaLocation="http://maven.apache.org/XDOC/2.0 http://maven.apache.org/xsd/xdoc-2.0.xsd">

	<properties>
		<title>JRebirth Analyzer</title>
		<author>Sébastien Bordes</author>
		<date>22/02/2013</date>
	</properties>

	<head>
		<meta name="keywords" lang="Fr" content="JavaFX 2 Demo Application Presentation" />
		<meta name="keywords" lang="En" content="JavaFX 2 Demo Application Presentation" />
		<meta name="description" content="JavaFx 2 JavaFx 2.0 Demo Application Presentation JRebirth Framework Lightning Talk" />
	</head>
	<body>

		<script type="text/javascript">//<![CDATA[
			var JAVAFX_APP_JNLP='analyzer/0.7.2/JRebirthAnalyzer.jnlp';
			var JAVAFX_APP_WIDTH=1024;
			var JAVAFX_APP_HEIGHT=768;
		//]]></script>
		<script type="text/javascript" src="../web-files/dtjava.js"></script>
		<script type="text/javascript" src="../web-files/javafxApp.js"></script>

		<section id="JRebirthAnalyzer" name="JRebirth Analyzer" >

			<p>This application can help you to debug your application</p>
			<p>
				Require
				<a href="http://www.oracle.com/technetwork/java/javafx/downloads/index.html">Java 7 with JavaFX 2 Runtime</a>
				(available for windows,
				<a href="http://www.oracle.com/technetwork/java/javafx/downloads/devpreview-1429449.html">mac and linux since 2.1</a>
				)
			</p>
			<br />
			<strong>Launch by Java Webstart:</strong>
			<a onclick="return launchApplication();">Click to launch this app as webstart</a>
			<br />
			Press F11 to activate fullscreen mode, use left-click to show the next slide, right click for previous slide
		
			<div style="margin: 10px;">
				You can browse the source code on
				<a title="JRebirth EclipseDay Repository" href="https://github.com/JRebirth/JRebirth/tree/master/org.jrebirth/analyzer" target="_blank">GitHub</a>
				.
				<br />
				<hr />
			</div>
			<div id="javafx-app-placeholder" style="margin: 0 -27px; padding: 0;">
			</div>

		</section>
	</body>
</document>


